deepcrawl/__init__.py
deepcrawl/exceptions.py
deepcrawl/utils.py
deepcrawl/accounts/__init__.py
deepcrawl/accounts/account.py
deepcrawl/accounts/connection.py
deepcrawl/api/__init__.py
deepcrawl/api/api.py
deepcrawl/api/api_endpoints.py
deepcrawl/api/request_headers.py
deepcrawl/crawls/__init__.py
deepcrawl/crawls/connection.py
deepcrawl/crawls/crawl.py
deepcrawl/crawls/schedule.py
deepcrawl/downloads/__init__.py
deepcrawl/downloads/connection.py
deepcrawl/downloads/download.py
deepcrawl/projects/__init__.py
deepcrawl/projects/connection.py
deepcrawl/projects/extractions.py
deepcrawl/projects/issues.py
deepcrawl/projects/majestic_settings.py
deepcrawl/projects/project_settings.py
deepcrawl/projects/projects.py
deepcrawl/reports/__init__.py
deepcrawl/reports/connection.py
deepcrawl/reports/report.py
deepcrawl/reports/report_row.py
deepcrawl-0.0.12.dist-info/LICENSE
deepcrawl-0.0.12.dist-info/METADATA
deepcrawl-0.0.12.dist-info/WHEEL
deepcrawl-0.0.12.dist-info/top_level.txt
deepcrawl-0.0.12.dist-info/RECORD
