Metadata-Version: 2.1
Name: deepcrawl
Version: 0.0.12
Summary: A package to simplify usage of the DeepCrawl REST API
Home-page: https://github.com/DeepCrawlSEO/dc_api_wrapper
Author: Andrei Mutu & Christopher Evans
Author-email: support@deepcrawl.com
License: UNKNOWN
Platform: UNKNOWN
Classifier: Programming Language :: Python :: 3
Classifier: License :: OSI Approved :: MIT License
Classifier: Operating System :: OS Independent
Requires-Python: >=3.6
Requires-Dist: certifi (==2019.11.28)
Requires-Dist: chardet (==3.0.4)
Requires-Dist: idna (==2.9)
Requires-Dist: requests (==2.23.0)
Requires-Dist: urllib3 (==1.25.8)
